README.md
setup.py
simptoolbox/__init__.py
simptoolbox/tlbx.py
simptoolbox.egg-info/PKG-INFO
simptoolbox.egg-info/SOURCES.txt
simptoolbox.egg-info/dependency_links.txt
simptoolbox.egg-info/requires.txt
simptoolbox.egg-info/top_level.txt