Metadata-Version: 2.1
Name: simptoolbox
Version: 0.1.1
Summary: Simple Class Manager
Home-page: https://github.com/StephenMal/simptoolbox
Author: Stephen Maldonado
Author-email: simptoolbox@stephenmal.com
License: UNKNOWN
Platform: UNKNOWN
Classifier: Development Status :: 1 - Planning
Classifier: Programming Language :: Python :: 3 :: Only
Classifier: Topic :: Utilities
